{"v":"5.6.9","fr":30,"ip":0,"op":600,"w":1600,"h":1600,"nm":"Raster/Vector-Test-01","ddd":0,"assets":[],"layers":[{"ddd":0,"ind":1,"ty":4,"nm":"Vector-Rect","sr":1,"ks":{"p":{"s":true,"x":{"a":1,"k":[{"i":{"x":[0.833],"y":[0.833]},"o":{"x":[0.167],"y":[0.167]},"t":0,"s":[292.582],"e":[1260.582]},{"i":{"x":[0.833],"y":[0.833]},"o":{"x":[0.167],"y":[0.167]},"t":41,"s":[1260.582],"e":[292.582]},{"i":{"x":[0.667],"y":[1]},"o":{"x":[0.167],"y":[0]},"t":90,"s":[292.582],"e":[292.582]},{"i":{"x":[0.394],"y":[1]},"o":{"x":[0.534],"y":[0]},"t":120,"s":[292.582],"e":[1260.582]},{"i":{"x":[0.488],"y":[1]},"o":{"x":[0.498],"y":[0]},"t":161,"s":[1260.582],"e":[292.582]},{"i":{"x":[0.667],"y":[1]},"o":{"x":[0.333],"y":[0]},"t":210,"s":[292.582],"e":[292.582]},{"i":{"x":[0.02],"y":[1]},"o":{"x":[1],"y":[0]},"t":235,"s":[292.582],"e":[1260.582]},{"i":{"x":[0.103],"y":[1]},"o":{"x":[0.991],"y":[0]},"t":276,"s":[1260.582],"e":[292.582]},{"t":325}]},"y":{"a":0,"k":389.316}},"a":{"a":0,"k":[-507.418,-410.684,0]}},"ao":0,"shapes":[{"ty":"gr","it":[{"ty":"rc","d":1,"s":{"a":0,"k":[200,200]},"p":{"a":0,"k":[0,0]},"r":{"a":0,"k":0},"nm":"Rectangle Path 1","hd":false},{"ty":"fl","c":{"a":0,"k":[0.212890804515,0.192156997381,0.96470600203,1]},"o":{"a":0,"k":100},"r":1,"bm":0,"nm":"Fill 1","hd":false},{"ty":"tr","p":{"a":0,"k":[-507.418,-410.684]},"a":{"a":0,"k":[0,0]},"s":{"a":0,"k":[100,100]},"r":{"a":0,"k":0},"o":{"a":0,"k":100},"sk":{"a":0,"k":0},"sa":{"a":0,"k":0},"nm":"Transform"}],"nm":"Rectangle 1","bm":0,"hd":false}],"ip":0,"op":516,"st":0,"bm":0}],"markers":[]}